soilspecdata/__init__.py
soilspecdata/_modidx.py
soilspecdata/types.py
soilspecdata/datasets/__init__.py
soilspecdata/datasets/ossl.py
soilspecdata-0.0.9.dist-info/LICENSE
soilspecdata-0.0.9.dist-info/METADATA
soilspecdata-0.0.9.dist-info/WHEEL
soilspecdata-0.0.9.dist-info/entry_points.txt
soilspecdata-0.0.9.dist-info/top_level.txt
soilspecdata-0.0.9.dist-info/RECORD
